rebrandly_otel/__init__.py
rebrandly_otel/api_gateway_utils.py
rebrandly_otel/fastapi_support.py
rebrandly_otel/flask_support.py
rebrandly_otel/http_constants.py
rebrandly_otel/http_utils.py
rebrandly_otel/logs.py
rebrandly_otel/metrics.py
rebrandly_otel/otel_utils.py
rebrandly_otel/pymysql_instrumentation.py
rebrandly_otel/rebrandly_otel.py
rebrandly_otel/redis_span_processor.py
rebrandly_otel/span_attributes_processor.py
rebrandly_otel/sqlite3_instrumentation.py
rebrandly_otel/traces.py
rebrandly_otel-0.4.14.dist-info/licenses/LICENSE
rebrandly_otel-0.4.14.dist-info/METADATA
rebrandly_otel-0.4.14.dist-info/WHEEL
rebrandly_otel-0.4.14.dist-info/top_level.txt
rebrandly_otel-0.4.14.dist-info/RECORD
