Metadata-Version: 2.4
Name: rebrandly_otel
Version: 0.4.14
Summary: Python OTEL wrapper by Rebrandly
Home-page: https://gitlab.rebrandly.com/rebrandly/instrumentation/rebrandly-otel-python
Author: Antonio Romano
Author-email: antonio@rebrandly.com
Classifier: Programming Language :: Python :: 3
Classifier: License :: OSI Approved :: MIT License
Classifier: Operating System :: OS Independent
Requires-Python: >=3.7
License-File: LICENSE
Requires-Dist: opentelemetry-api>=1.35.0
Requires-Dist: opentelemetry-sdk>=1.35.0
Requires-Dist: opentelemetry-exporter-otlp>=1.35.0
Requires-Dist: opentelemetry-semantic-conventions>=0.60b0
Requires-Dist: opentelemetry-instrumentation-redis>=0.60b0
Requires-Dist: opentelemetry-instrumentation-botocore>=0.48b0
Requires-Dist: psutil>=5.0.0
Provides-Extra: flask
Requires-Dist: flask>=2.0.0; extra == "flask"
Requires-Dist: werkzeug>=2.0.0; extra == "flask"
Provides-Extra: fastapi
Requires-Dist: fastapi>=0.118.0; extra == "fastapi"
Requires-Dist: starlette>=0.32.0; extra == "fastapi"
Requires-Dist: uvicorn>=0.20.0; extra == "fastapi"
Provides-Extra: all
Requires-Dist: flask>=2.0.0; extra == "all"
Requires-Dist: werkzeug>=2.0.0; extra == "all"
Requires-Dist: fastapi>=0.118.0; extra == "all"
Requires-Dist: starlette>=0.32.0; extra == "all"
Requires-Dist: uvicorn>=0.20.0; extra == "all"
Dynamic: author
Dynamic: author-email
Dynamic: classifier
Dynamic: description
Dynamic: description-content-type
Dynamic: home-page
Dynamic: license-file
Dynamic: provides-extra
Dynamic: requires-dist
Dynamic: requires-python
Dynamic: summary
